MANIFEST.in
README.rst
setup.cfg
setup.py
ansible_role_manager.egg-info/PKG-INFO
ansible_role_manager.egg-info/SOURCES.txt
ansible_role_manager.egg-info/dependency_links.txt
ansible_role_manager.egg-info/requires.txt
ansible_role_manager.egg-info/top_level.txt
arm/__init__.py
arm/_version.py
arm/conf.py
arm/defaults.ini
arm/main.py
arm/odict.py
arm/prompt.py
arm/util.py
arm/commands/__init__.py
arm/commands/freeze.py
arm/commands/help.py
arm/commands/init.py
arm/commands/install.py
arm/commands/uninstall.py
arm/commands/update.py
arm/commands/init/module/main.py.armj2
arm/commands/init/playbook/.arm.armj2
arm/commands/init/playbook/.gitignore.armj2
arm/commands/init/playbook/myplaybookname.yml
arm/commands/init/playbook/production
arm/commands/init/playbook/site.yml
arm/commands/init/playbook/.installed_modules/.gitignore
arm/commands/init/playbook/.installed_roles/.gitignore
arm/commands/init/playbook/group_vars/production1
arm/commands/init/playbook/group_vars/production2
arm/commands/init/playbook/host_vars/production1a.example.com
arm/commands/init/playbook/host_vars/production2b.example.com
arm/commands/init/playbook/library/README
arm/commands/init/playbook/roles/README
arm/commands/init/role/README.md
arm/commands/init/role/defaults/main.yml
arm/commands/init/role/files/bar.txt
arm/commands/init/role/files/foo.sh
arm/commands/init/role/handlers/main.yml
arm/commands/init/role/meta/main.yml
arm/commands/init/role/tasks/main.yml.arm
arm/commands/init/role/templates/example.cfg.j2
arm/commands/init/role/vars/main.yml
arm/routes/__init__.py
arm/routes/bzr.py
arm/routes/galaxy.py
arm/routes/git.py
arm/routes/hg.py
arm/routes/local.py
arm/routes/svn.py
arm/routes/url.py
bin/arm