Metadata-Version: 1.0
Name: ansible-role-manager
Version: 0.4
Summary: A tool for installing and managing Ansible roles, playbooks & modules.
Home-page: http://mirskytech.github.io/ansible-role-manager/
Author: Andrew Mirsky
Author-email: andrew@mirskytech.com
License: UNKNOWN
Platform: UNKNOWN
